orderPy.py
orderPy-1.0.data/scripts/orderPy.py
orderPy-1.0.dist-info/DESCRIPTION.rst
orderPy-1.0.dist-info/METADATA
orderPy-1.0.dist-info/RECORD
orderPy-1.0.dist-info/WHEEL
orderPy-1.0.dist-info/entry_points.txt
orderPy-1.0.dist-info/metadata.json
orderPy-1.0.dist-info/top_level.txt
