Metadata-Version: 2.0
Name: orderPy
Version: 1.0
Summary: A python script for windows that will order a disordered set of files by their date of creation or last modification.
Home-page: https://github.com/johannesber/orderPy
Author: Johannes Berger
Author-email: johannes.berger1709@gmail.com
License: MIT
Keywords: sorting data
Platform: UNKNOWN
Classifier: Development Status :: 5 - Production/Stable
Classifier: Intended Audience :: End Users/Desktop
Classifier: Topic :: Desktop Environment :: File Managers
Classifier: License :: OSI Approved :: MIT License
Classifier: Programming Language :: Python :: 3.6
Classifier: Operating System :: Microsoft :: Windows
Requires-Python: >3.6
Requires-Dist: Unipath
Requires-Dist: pip
